flask_restx_patched/__init__.py
flask_restx_patched/_http.py
flask_restx_patched/api.py
flask_restx_patched/errors.py
flask_restx_patched/model.py
flask_restx_patched/namespace.py
flask_restx_patched/parameters.py
flask_restx_patched/resource.py
flask_restx_patched/swagger.py
wbia/__init__.py
wbia/__main__.py
wbia/_devcmds_wbia.py
wbia/_devscript.py
wbia/_version.py
wbia/_wbia_object.py
wbia/annotmatch_funcs.py
wbia/annots.py
wbia/conftest.py
wbia/constants.py
wbia/core_annots.py
wbia/core_images.py
wbia/core_parts.py
wbia/demodata.py
wbia/dev.py
wbia/entry_points.py
wbia/filter_configs.py
wbia/images.py
wbia/params.py
wbia/tag_funcs.py
wbia/utils.py
wbia/algo/Config.py
wbia/algo/__init__.py
wbia/algo/detect/__init__.py
wbia/algo/detect/assigner.py
wbia/algo/detect/azure.py
wbia/algo/detect/canonical.py
wbia/algo/detect/darknet.py
wbia/algo/detect/densenet.py
wbia/algo/detect/fasterrcnn.py
wbia/algo/detect/grabmodels.py
wbia/algo/detect/lightnet.py
wbia/algo/detect/orientation.py
wbia/algo/detect/randomforest.py
wbia/algo/detect/rf.py
wbia/algo/detect/selectivesearch.py
wbia/algo/detect/ssd.py
wbia/algo/detect/svm.py
wbia/algo/detect/train_assigner.py
wbia/algo/detect/yolo.py
wbia/algo/detect/nms/.gitignore
wbia/algo/detect/nms/__init__.py
wbia/algo/detect/nms/py_cpu_nms.py
wbia/algo/graph/__init__.py
wbia/algo/graph/__main__.py
wbia/algo/graph/core.py
wbia/algo/graph/demo.py
wbia/algo/graph/mixin_dynamic.py
wbia/algo/graph/mixin_groundtruth.py
wbia/algo/graph/mixin_helpers.py
wbia/algo/graph/mixin_loops.py
wbia/algo/graph/mixin_matching.py
wbia/algo/graph/mixin_priority.py
wbia/algo/graph/mixin_simulation.py
wbia/algo/graph/mixin_viz.py
wbia/algo/graph/mixin_wbia.py
wbia/algo/graph/nx_dynamic_graph.py
wbia/algo/graph/nx_edge_augmentation.py
wbia/algo/graph/nx_edge_kcomponents.py
wbia/algo/graph/nx_utils.py
wbia/algo/graph/refresh.py
wbia/algo/graph/state.py
wbia/algo/graph/tests/__init__.py
wbia/algo/graph/tests/dyn_cases.py
wbia/algo/graph/tests/mst_debug.py
wildbook_ia-4.0.4.dist-info/LICENSE.txt
wildbook_ia-4.0.4.dist-info/METADATA
wildbook_ia-4.0.4.dist-info/WHEEL
wildbook_ia-4.0.4.dist-info/entry_points.txt
wildbook_ia-4.0.4.dist-info/top_level.txt
wildbook_ia-4.0.4.dist-info/RECORD
